{
    "_publish_status": "draft",
    "author_name": "afropolymath",
    "author_real_name": "Chidiebere Nnadi",
    "branch": "master",
    "branches": [],
    "filename": "article.md",
    "first_commit": "7aef3d165fe243fb869fdea586b470cffcd5d81e",
    "image_url": "https://avatars.githubusercontent.com/u/3100850?v=3",
    "stacks": [
        "Front-End JavaScript (Angular, React, Meteor, etc)"
    ],
    "thumbnail_url": null,
    "title": "Build a simple File storage service using VueJS, Flask and RethinkDB (Frontend)"
}